apifonica_client/__init__.py
ApifonicaClient-1.0.1.dist-info/LICENSE
ApifonicaClient-1.0.1.dist-info/METADATA
ApifonicaClient-1.0.1.dist-info/WHEEL
ApifonicaClient-1.0.1.dist-info/top_level.txt
ApifonicaClient-1.0.1.dist-info/RECORD
