Metadata-Version: 2.1
Name: ApifonicaClient
Version: 1.0.1
Summary: Unofficial Python Package to easily integrate the Apifonica API to your project
Author: Paul Harrer
Author-email: mail@paulharrer.at
Project-URL: GitHub, https://github.com/PaulHarrer/apifonica-client
License-File: LICENSE
Requires-Dist: requests
